ytsort/__main__.py
ytsort/cache_manager.py
ytsort/config.py
ytsort/data_store.py
ytsort/my_io.py
ytsort/renamer.py
ytsort/youtube.py
ytsort-1.4.0.dist-info/LICENSE.md
ytsort-1.4.0.dist-info/WHEEL
ytsort-1.4.0.dist-info/METADATA
ytsort-1.4.0.dist-info/entry_points.txt
ytsort-1.4.0.dist-info/RECORD
