Metadata-Version: 2.1
Name: ytsort
Version: 1.4.0
Summary: Arrange downloaded youtube videos
Home-page: https://github.com/aqdasak/YTSort/
License: MIT
Keywords: python,youtube,sort,youtube-playlist,youtube-data-api-v3
Author: Aqdas Ahmad Khan
Author-email: aqdasak@gmail.com
Requires-Python: >=3.10,<4.0
Classifier: License :: OSI Approved :: MIT License
Classifier: Programming Language :: Python :: 3
Classifier: Programming Language :: Python :: 3.10
Classifier: Programming Language :: Python :: 3.11
Requires-Dist: alive-progress (==1.6.2)
Requires-Dist: click (>=8.0.3,<9.0.0)
Requires-Dist: colorama (>=0.3.7,<0.4.0)
Requires-Dist: google-api-python-client (>=2.8.0,<3.0.0)
Project-URL: Repository, https://github.com/aqdasak/YTSort/
